menufather/__init__.py
menufather/menuMaker.py
menufather-1.5.0.dist-info/LICENSE
menufather-1.5.0.dist-info/METADATA
menufather-1.5.0.dist-info/WHEEL
menufather-1.5.0.dist-info/top_level.txt
menufather-1.5.0.dist-info/RECORD
