Metadata-Version: 2.1
Name: menufather
Version: 1.5.0
Summary: a library for creating console-based menus (linux / windows)
Author-email: MrPythonBlog <mrpythonblog@gmail.com>
License: MIT License        
Project-URL: Homepage, https://github.com/mrpythonblog/menufather
Classifier: License :: OSI Approved :: MIT License
Classifier: Programming Language :: Python
Classifier: Programming Language :: Python :: 3
Requires-Python: >=3.5
License-File: LICENSE
Requires-Dist: colorama
Requires-Dist: cursor
Requires-Dist: pynput
